sign_off/__init__.py
sign_off/sign_off.py
sign_off-0.1.0.dist-info/entry_points.txt
sign_off-0.1.0.dist-info/LICENSE
sign_off-0.1.0.dist-info/WHEEL
sign_off-0.1.0.dist-info/METADATA
sign_off-0.1.0.dist-info/RECORD
